dragonfly_grasshopper/__init__.py
dragonfly_grasshopper/src/DF Align.py
dragonfly_grasshopper/src/DF All-Air HVAC.py
dragonfly_grasshopper/src/DF Apply Facade Parameters.py
dragonfly_grasshopper/src/DF Apply Roof.py
dragonfly_grasshopper/src/DF Assign Building UWG Properties.py
dragonfly_grasshopper/src/DF Assign DES Building Loads.py
dragonfly_grasshopper/src/DF Assign Model UWG Properties.py
dragonfly_grasshopper/src/DF Boundary Layer Parameters.py
dragonfly_grasshopper/src/DF Building from Detailed Rooms.py
dragonfly_grasshopper/src/DF Building from Footprint.py
dragonfly_grasshopper/src/DF Building from Solid.py
dragonfly_grasshopper/src/DF Building from Stories.py
dragonfly_grasshopper/src/DF Color Network Attributes.py
dragonfly_grasshopper/src/DF Color Network Results.py
dragonfly_grasshopper/src/DF Color Room2D Attributes.py
dragonfly_grasshopper/src/DF Construct Design Day.py
dragonfly_grasshopper/src/DF ContextShade.py
dragonfly_grasshopper/src/DF Create EPW.py
dragonfly_grasshopper/src/DF DOAS HVAC.py
dragonfly_grasshopper/src/DF Deconstruct All Object.py
dragonfly_grasshopper/src/DF Deconstruct Model.py
dragonfly_grasshopper/src/DF Deconstruct Object.py
dragonfly_grasshopper/src/DF Deconstruct OpenDSS.py
dragonfly_grasshopper/src/DF Deconstruct Roof.py
dragonfly_grasshopper/src/DF Detailed HVAC.py
dragonfly_grasshopper/src/DF Detailed Skylights.py
dragonfly_grasshopper/src/DF Detailed Windows.py
dragonfly_grasshopper/src/DF Diversify Building Programs.py
dragonfly_grasshopper/src/DF Dump Objects.py
dragonfly_grasshopper/src/DF Electrical Connector.py
dragonfly_grasshopper/src/DF Electrical Network.py
dragonfly_grasshopper/src/DF Extruded Border Parameters.py
dragonfly_grasshopper/src/DF Fourth Generation Thermal Loop.py
dragonfly_grasshopper/src/DF GHE Borehole Parameter.py
dragonfly_grasshopper/src/DF GHE Design Parameter.py
dragonfly_grasshopper/src/DF GHE Designer.py
dragonfly_grasshopper/src/DF GHE Fluid Parameter.py
dragonfly_grasshopper-1.64.1.dist-info/licenses/LICENSE
dragonfly_grasshopper-1.64.1.dist-info/METADATA
dragonfly_grasshopper-1.64.1.dist-info/WHEEL
dragonfly_grasshopper-1.64.1.dist-info/top_level.txt
dragonfly_grasshopper-1.64.1.dist-info/RECORD
